mathics3_graph-9.0.0.dist-info/licenses/LICENSE
pymathics/graph/__init__.py
pymathics/graph/base.py
pymathics/graph/boxes.py
pymathics/graph/centralities.py
pymathics/graph/collections.py
pymathics/graph/components.py
pymathics/graph/curated.py
pymathics/graph/format.py
pymathics/graph/graphsymbols.py
pymathics/graph/measures_and_metrics.py
pymathics/graph/operations.py
pymathics/graph/parametric.py
pymathics/graph/properties.py
pymathics/graph/random.py
pymathics/graph/structured.py
pymathics/graph/tree.py
pymathics/graph/version.py
pymathics/graph/eval/__init__.py
pymathics/graph/eval/harary.py
pymathics/graph/eval/parametric.py
pymathics/graph/eval/tree.py
mathics3_graph-9.0.0.dist-info/METADATA
mathics3_graph-9.0.0.dist-info/WHEEL
mathics3_graph-9.0.0.dist-info/top_level.txt
mathics3_graph-9.0.0.dist-info/RECORD
